{
  "frames": {
    "9": { "frame": { "x": 0, "y": 0, "w": 1024, "h": 1024 } },
    "10": { "frame": { "x": 0, "y": 1025, "w": 1024, "h": 1024 } },
    "Ace": { "frame": { "x": 1025, "y": 0, "w": 1024, "h": 1024 } },
    "B": { "frame": { "x": 1025, "y": 1025, "w": 1024, "h": 1024 } },
    "C": { "frame": { "x": 0, "y": 2050, "w": 1024, "h": 1024 } },
    "D": { "frame": { "x": 1025, "y": 2050, "w": 1024, "h": 1024 } },
    "Jack": { "frame": { "x": 2050, "y": 0, "w": 1024, "h": 1024 } },
    "King": { "frame": { "x": 2050, "y": 1025, "w": 1024, "h": 1024 } },
    "Queen": { "frame": { "x": 2050, "y": 2050, "w": 1024, "h": 1024 } },
    "S": { "frame": { "x": 0, "y": 3075, "w": 1024, "h": 1024 } },
    "Z": { "frame": { "x": 1025, "y": 3075, "w": 1024, "h": 1024 } }
  },
  "meta": {
    "version": "1.0",
    "image": "spritesheet.png",
    "format": "RGBA8888",
    "size": { "w": 3074, "h": 4099 },
    "scale": "1"
  }
}
